topsis_prak_3844/__init__.py
topsis_prak_3844/topsis.py
topsis_prak_3844-1.0.1.dist-info/LICENSE
topsis_prak_3844-1.0.1.dist-info/METADATA
topsis_prak_3844-1.0.1.dist-info/WHEEL
topsis_prak_3844-1.0.1.dist-info/top_level.txt
topsis_prak_3844-1.0.1.dist-info/RECORD
